{"@class":"TimeLineScript","id":{"uuid":"03F76855-D66B-464A-8465-0CD39948B31F"},"name":"Animation","enableOnAwake":false,"loop":true,"jumpToFirstFrameAtEnd":false,"speed":0.0,"weight":0.0,"loopStartTime":0,"loopDuration":0,"is_imported":false,"type":"user","scripts":{"@class":"StdListRuntimeScript","list":[{"@class":"AnimationScript","id":{"uuid":"C42C8902-9E5B-4B08-B13A-545F9233794E"},"name":"Top","enableOnAwake":false,"OwnerLink":{"@class":"BindingLink","targetId":{"uuid":"A348AC76-AAC5-4129-988F-57AD5EB45EEE"},"targetRelativeAddress":{"@class":"NodeRelativeAddressBase","index":0,"name":"Drone 2","subaddress":{"@class":"NodeRelativeAddressBase","index":2,"name":"Base Y","subaddress":{"@class":"NodeRelativeAddressBase","index":0,"name":"Base X","subaddress":{"@class":"NodeRelativeAddressBase","index":0,"name":"Top"}}}}},"animation":{"uuid":"4C39199B-90F1-48A4-A8DA-601C733AE939"},"AnimationType":"object3D","is_imported":false,"isEnabled":true},{"@class":"AnimationScript","id":{"uuid":"60A35200-315A-4D71-B6CC-76B26968BAC8"},"name":"Drone 2","enableOnAwake":false,"OwnerLink":{"@class":"BindingLink","targetId":{"uuid":"2380CCC4-8B7C-4510-A3D5-04612AA84AD2"}},"animation":{"uuid":"50A3F37B-7B4B-464A-AD30-D518FC3B6C9E"},"AnimationType":"object3D","is_imported":false,"isEnabled":true},{"@class":"AnimationScript","id":{"uuid":"E8B7FA28-FFB7-4D3C-8BAC-94CFA872AAC1"},"name":"Drone 2","enableOnAwake":false,"OwnerLink":{"@class":"BindingLink","targetId":{"uuid":"51C3A4EB-3448-4559-B927-83E5AD1DE4EE"},"targetRelativeAddress":{"@class":"NodeRelativeAddressBase","index":0,"name":"Drone 2"}},"animation":{"uuid":"F952D19F-E48C-4836-88BD-8144E0E4DAC8"},"AnimationType":"object3D","is_imported":false,"isEnabled":false}]},"triggers":[{"@class":"StateMachineTrigger","id":{"uuid":"FCD67C09-F7C5-4BAD-B87B-8FDF5B5909DB"},"ownerScriptId":{"uuid":"03F76855-D66B-464A-8465-0CD39948B31F"},"logicOperation":0,"resultType":0,"isInverted":false,"event":3,"stateBindingLink":{"@class":"BindingLink","targetId":{"uuid":"6D80661E-FA7E-4C2E-A9EB-CD273728E414"}},"objectBindingLink":{"@class":"BindingLink","targetId":{"uuid":"1B05D8F4-789D-4619-92A3-77FC53D41324"}}},{"@class":"CollisionTrigger","id":{"uuid":"22B38853-8C60-4C04-844C-C66444B45A06"},"ownerScriptId":{"uuid":"03F76855-D66B-464A-8465-0CD39948B31F"},"logicOperation":1,"resultType":3,"isInverted":false,"eventType":"outside","targetBindingLink":{"@class":"BindingLink","targetId":{"uuid":"25FE1577-F604-4D13-ACCD-656144CA9EBD"}},"zoneBindingLink":{"@class":"BindingLink","targetId":{"uuid":"89853758-124B-436F-989E-188BCEF20745"}}},{"@class":"AnimationTrigger","id":{"uuid":"CC0932E0-3D4C-4E7C-944C-CDACCC340491"},"ownerScriptId":{"uuid":"03F76855-D66B-464A-8465-0CD39948B31F"},"logicOperation":0,"resultType":0,"isInverted":false,"event":1,"bindingLink":{"@class":"BindingLink","targetId":{"uuid":"3F525CC5-6EA6-498D-B248-F05797EA7084"}}}]}