{"@class":"TimeLineScript","id":{"uuid":"13CE5631-28F7-4DC8-9836-C9D11DB7C02B"},"name":"Animation","enableOnAwake":false,"loop":true,"jumpToFirstFrameAtEnd":false,"speed":1.0,"weight":1.0,"loopStartTime":0,"loopDuration":0,"is_imported":false,"type":"user","scripts":{"@class":"StdListRuntimeScript","list":[{"@class":"AnimationScript","id":{"uuid":"1AFB28C7-3D31-491E-A402-926AE1B3538B"},"name":"Drone_T-pose","enableOnAwake":false,"OwnerLink":{"@class":"BindingLink","targetId":{"uuid":"22B8E9DA-3FA4-43F4-B967-0A2B1DCEAE9F"},"targetRelativeAddress":{"@class":"NodeRelativeAddressBase","index":0,"name":"Drone 2","subaddress":{"@class":"NodeRelativeAddressBase","index":1,"name":"Drone_T-pose","subaddress":{"@class":"NodeRelativeAddressBase","index":1,"name":"Armature","subaddress":{"@class":"NodeRelativeAddressBase","index":0,"name":"BaseDR2","subaddress":{"@class":"NodeRelativeAddressBase","index":0,"name":"Body"}}}}}},"animation":{"uuid":"C61A729A-9C9A-42DE-A13B-A487A8F05F62"},"AnimationType":"object3D","is_imported":false,"isEnabled":true},{"@class":"AnimationScript","id":{"uuid":"6E16F62F-D1D1-4587-9C3D-05D8CD9D3D09"},"name":"Angle","enableOnAwake":false,"OwnerLink":{"@class":"BindingLink","targetId":{"uuid":"A401D28E-3748-4265-B22E-E42F49227D5B"}},"animation":{"uuid":"3E44A45C-F75F-445C-ACA6-173535D24EC5"},"AnimationType":"avar","is_imported":false,"isEnabled":true}]},"triggers":[{"@class":"CompareTrigger","id":{"uuid":"E1F9E290-B5DA-44C8-A48C-B48F2359592B"},"ownerScriptId":{"uuid":"13CE5631-28F7-4DC8-9836-C9D11DB7C02B"},"logicOperation":0,"resultType":0,"isInverted":false,"operation":"==","eventType":"result_true","leftOperand":"object__51C3A4EB_3448_4559_B927_83E5AD1DE4EE__flyingSpeed","rightOperand":"0"},{"@class":"AnimationTrigger","id":{"uuid":"E877377E-0DE5-4108-BBE8-D3069BEC68F9"},"ownerScriptId":{"uuid":"13CE5631-28F7-4DC8-9836-C9D11DB7C02B"},"logicOperation":1,"resultType":0,"isInverted":false,"event":1,"bindingLink":{"@class":"BindingLink","targetId":{"uuid":"88D81D95-A1E0-4F55-AF98-ED2323E7CBB4"}}},{"@class":"AnimationTrigger","id":{"uuid":"386A9790-1C3A-41C8-8953-102121377AF8"},"ownerScriptId":{"uuid":"13CE5631-28F7-4DC8-9836-C9D11DB7C02B"},"logicOperation":0,"resultType":0,"isInverted":false,"event":3,"bindingLink":{"@class":"BindingLink","targetId":{"uuid":"5AE3774C-3ABD-4161-8D20-C3CE84076292"}}}],"symbolTable":{"@class":"VariousSymbolTable","id":{"uuid":"3D16FB91-B235-4FC7-BADA-59C35BE7EFCC"},"variables":[{"@class":"VariantVariable","id":{"uuid":"A401D28E-3748-4265-B22E-E42F49227D5B"},"name":"Angle","type":"float","value":0.0}]}}