{"@class":"TimeLineScript","id":{"uuid":"16C9822B-1159-4899-89C9-575136F26D85"},"name":"Animation","enableOnAwake":false,"loop":true,"jumpToFirstFrameAtEnd":false,"speed":1.0,"weight":1.0,"loopStartTime":0,"loopDuration":0,"is_imported":false,"type":"user","scripts":{"@class":"StdListRuntimeScript","list":[{"@class":"AnimationScript","id":{"uuid":"796C7650-1E24-47AA-82FB-766E82BAE35E"},"name":"Tag Animation","enableOnAwake":false,"OwnerLink":{"@class":"BindingLink","tagId":{"uuid":"7CA4B06D-1192-4559-B6EB-2DD59B902AFF"}},"animation":{"uuid":"9C2815B3-AF89-4A6F-8F2B-F42B337BEC9B"},"AnimationType":"tag","is_imported":false,"isEnabled":true},{"@class":"AnimationScript","id":{"uuid":"8799387A-3DDF-4B5C-AA75-E3E28CDA89AD"},"name":"Tag Animation","enableOnAwake":false,"OwnerLink":{"@class":"BindingLink","tagId":{"uuid":"A0D8C3AE-5405-497C-B194-183EE78080C3"}},"animation":{"uuid":"BC4140E2-7E6B-4F20-9862-3082A9DF69AD"},"AnimationType":"tag","is_imported":false,"isEnabled":true}]},"triggers":[{"@class":"CollisionTrigger","id":{"uuid":"2444F7AE-C6DD-449E-9EBD-F11A7C1DEDCA"},"ownerScriptId":{"uuid":"16C9822B-1159-4899-89C9-575136F26D85"},"logicOperation":0,"resultType":0,"isInverted":false,"eventType":"in","targetBindingLink":{"@class":"BindingLink","targetId":{"uuid":"25FE1577-F604-4D13-ACCD-656144CA9EBD"}},"zoneBindingLink":{"@class":"BindingLink","tagId":{"uuid":"BA38A137-D499-4A7C-BDE8-CB97856023E6"}}},{"@class":"CollisionTrigger","id":{"uuid":"9DD93130-9793-4139-8BC4-103908714356"},"ownerScriptId":{"uuid":"16C9822B-1159-4899-89C9-575136F26D85"},"logicOperation":1,"resultType":0,"isInverted":true,"eventType":"out","targetBindingLink":{"@class":"BindingLink","targetId":{"uuid":"25FE1577-F604-4D13-ACCD-656144CA9EBD"}},"zoneBindingLink":{"@class":"BindingLink","tagId":{"uuid":"BA38A137-D499-4A7C-BDE8-CB97856023E6"}}}]}