{"@class":"TimeLineScript","id":{"uuid":"1F3A99C8-FB29-4132-99C7-FB8D441E1EAB"},"name":"Animation","enableOnAwake":false,"loop":false,"jumpToFirstFrameAtEnd":false,"speed":1.0,"weight":1.0,"loopStartTime":0,"loopDuration":0,"is_imported":false,"type":"user","scripts":{"@class":"StdListRuntimeScript","list":[{"@class":"AnimationScript","id":{"uuid":"EE79EB49-559B-49A3-8B8D-5DD8EDA26596"},"name":"Selected Point","enableOnAwake":false,"OwnerLink":{"@class":"BindingLink","targetId":{"uuid":"588D66DA-84B0-4CD2-AB71-BBF5DD015FBB"}},"animation":{"uuid":"9DC298C7-E831-4EFE-8438-71D43DADBB3E"},"AnimationType":"object3D","is_imported":false,"isEnabled":true},{"@class":"AnimationScript","id":{"uuid":"E79E5E3F-C362-45C5-9B88-C701AE63D1D4"},"name":"Target Zone","enableOnAwake":false,"OwnerLink":{"@class":"BindingLink","targetId":{"uuid":"0662A1D3-3EF4-40F1-A091-20849898DCE4"}},"animation":{"uuid":"52FC5DB2-8169-4E66-A0AD-3DF90E8DE788"},"AnimationType":"object3D","is_imported":false,"isEnabled":true},{"@class":"AnimationScript","id":{"uuid":"D2CAEC84-ED4D-47EA-8E8E-3E1E876D4400"},"name":"Healing_Collider","enableOnAwake":false,"OwnerLink":{"@class":"BindingLink","targetId":{"uuid":"1D8693FB-A295-4723-9F1E-60819E911214"}},"animation":{"uuid":"63D1E413-85D1-49F5-9BF6-AFE3759547AC"},"AnimationType":"object3D","is_imported":false,"isEnabled":true}]},"triggers":[{"@class":"CompareTrigger","id":{"uuid":"009E2C5A-49A6-4EA2-9133-73369FF02799"},"ownerScriptId":{"uuid":"1F3A99C8-FB29-4132-99C7-FB8D441E1EAB"},"logicOperation":0,"resultType":0,"isInverted":false,"operation":"<=","eventType":"result_true_started","leftOperand":"object__5E0312A0_331E_4A16_8313_921EF4FBDE3A__health_now","rightOperand":"33"}]}