{"@class":"TimeLineScript","id":{"uuid":"24CBCBC7-2C0F-4BD4-ADEE-CA6F4963A14D"},"name":"Animation","enableOnAwake":false,"loop":false,"jumpToFirstFrameAtEnd":false,"speed":1.0,"weight":1.0,"loopStartTime":0,"loopDuration":0,"is_imported":false,"type":"user","scripts":{"@class":"StdListRuntimeScript","list":[{"@class":"AnimationScript","id":{"uuid":"09CE06D5-0512-4EBD-8557-6A07D617495F"},"name":"Respawn Bot Target","enableOnAwake":false,"OwnerLink":{"@class":"BindingLink","targetId":{"uuid":"31419B9C-D245-4DE1-9E65-3F65A113BADE"},"targetRelativeAddress":{"@class":"NodeRelativeAddressBase","index":1,"name":"Model","subaddress":{"@class":"NodeRelativeAddressBase","index":6,"name":"Respawn Bot Target"}}},"animation":{"uuid":"F6CD53BB-0DB2-4CA0-A3E9-B50EE9CA27FF"},"AnimationType":"object3D","is_imported":false,"isEnabled":true},{"@class":"AnimationScript","id":{"uuid":"77484A30-7EC7-46DA-9832-FBA44F826B6A"},"name":"AnimationScript","enableOnAwake":false,"OwnerLink":{"@class":"BindingLink","targetId":{"uuid":"7BCBEBA1-14C5-40F2-8857-C599B6EAAC76"}},"animation":{"uuid":"2A012351-0F9D-4B44-9FD0-8CE2EF86002C"},"AnimationType":"object3D","is_imported":false,"isEnabled":true}]},"triggers":[{"@class":"KeyTrigger","id":{"uuid":"DDCB639A-71EB-481E-B1A1-691D98A0A938"},"ownerScriptId":{"uuid":"24CBCBC7-2C0F-4BD4-ADEE-CA6F4963A14D"},"logicOperation":1,"resultType":0,"isInverted":true,"keyCode":87,"state":1},{"@class":"KeyTrigger","id":{"uuid":"489B3D0B-F5EC-463F-A30A-9BDAF5DA791A"},"ownerScriptId":{"uuid":"24CBCBC7-2C0F-4BD4-ADEE-CA6F4963A14D"},"logicOperation":1,"resultType":0,"isInverted":true,"keyCode":65,"state":1},{"@class":"KeyTrigger","id":{"uuid":"190A2178-70B8-436A-A86E-B34D414B9602"},"ownerScriptId":{"uuid":"24CBCBC7-2C0F-4BD4-ADEE-CA6F4963A14D"},"logicOperation":1,"resultType":0,"isInverted":true,"keyCode":68,"state":1},{"@class":"KeyTrigger","id":{"uuid":"FBC96843-8322-40C9-841F-08CE11589FFE"},"ownerScriptId":{"uuid":"24CBCBC7-2C0F-4BD4-ADEE-CA6F4963A14D"},"logicOperation":1,"resultType":0,"isInverted":true,"keyCode":83,"state":1},{"@class":"CollisionTrigger","id":{"uuid":"1CC5CBAE-0A40-4487-ADE3-5F838E1A40FF"},"ownerScriptId":{"uuid":"24CBCBC7-2C0F-4BD4-ADEE-CA6F4963A14D"},"logicOperation":1,"resultType":0,"isInverted":true,"eventType":"inside","targetBindingLink":{"@class":"BindingLink","targetId":{"uuid":"25FE1577-F604-4D13-ACCD-656144CA9EBD"}},"zoneBindingLink":{"@class":"BindingLink","targetId":{"uuid":"82C7A1AC-86BD-41E4-AEE4-1D668FAE9C78"}}},{"@class":"AnimationTrigger","id":{"uuid":"E1EA0949-3D09-4493-9736-6E8B3149C000"},"ownerScriptId":{"uuid":"24CBCBC7-2C0F-4BD4-ADEE-CA6F4963A14D"},"logicOperation":1,"resultType":0,"isInverted":true,"event":3,"bindingLink":{"@class":"BindingLink","targetId":{"uuid":"BF1EEB2C-82CE-45C0-BEE6-29E160A75BAF"}}}]}