{"@class":"TimeLineScript","id":{"uuid":"25DDB697-22ED-4A9A-B7F6-761A71B46E6A"},"name":"Xplosion.fbx","enableOnAwake":false,"loop":false,"jumpToFirstFrameAtEnd":false,"speed":1.0,"weight":1.0,"loopStartTime":0,"loopDuration":0,"is_imported":true,"type":"user","scripts":{"@class":"StdListRuntimeScript","list":[{"@class":"AnimationScript","id":{"uuid":"72EB7631-7CE3-482B-A799-B7DC67E0A2D1"},"name":"AnimationScript","enableOnAwake":false,"OwnerLink":{"@class":"BindingLink","targetId":{"uuid":"A70D26DB-0A98-4415-BFE1-2628A27B52CF"}},"animation":{"uuid":"55922FCA-E83E-4A41-8216-B2FCC7BE0E4A"},"AnimationType":"object3D","is_imported":true,"isEnabled":true},{"@class":"AnimationScript","id":{"uuid":"4DBE5E1A-F52C-4B72-8653-736DD5ABACAB"},"name":"AnimationScript","enableOnAwake":false,"OwnerLink":{"@class":"BindingLink","targetId":{"uuid":"4A81F632-C0E4-4655-8C16-363FBD1C9204"}},"animation":{"uuid":"B6BFFE51-DAFE-45ED-8CB3-4E33B1DD9D5C"},"AnimationType":"object3D","is_imported":true,"isEnabled":true},{"@class":"AnimationScript","id":{"uuid":"1D1276FF-CFFA-4143-A1DE-7E3E006CE865"},"name":"AnimationScript","enableOnAwake":false,"OwnerLink":{"@class":"BindingLink","targetId":{"uuid":"47B36722-7654-4852-80C2-A45405D39790"}},"animation":{"uuid":"F06B416C-1AE9-448A-AC35-7C87AF96973C"},"AnimationType":"object3D","is_imported":true,"isEnabled":true},{"@class":"AnimationScript","id":{"uuid":"89C75B35-B326-4B4D-83A7-598523CB2DCA"},"name":"AnimationScript","enableOnAwake":false,"OwnerLink":{"@class":"BindingLink","targetId":{"uuid":"4516918F-084B-4415-AADE-3690030D5B5E"}},"animation":{"uuid":"8D121868-260B-48D4-924E-79A81B256B5A"},"AnimationType":"object3D","is_imported":true,"isEnabled":true},{"@class":"AnimationScript","id":{"uuid":"21875D1D-FDEE-4459-8364-104B58CAB343"},"name":"AnimationScript","enableOnAwake":false,"OwnerLink":{"@class":"BindingLink","targetId":{"uuid":"924D4E9E-2B85-4F42-B311-6595FA59FDD1"}},"animation":{"uuid":"9DC05311-B67F-4DC7-9C03-91B513C99F29"},"AnimationType":"object3D","is_imported":true,"isEnabled":true},{"@class":"AnimationScript","id":{"uuid":"757AA75B-98CC-4394-B4BC-AC8ACFB62A11"},"name":"AnimationScript","enableOnAwake":false,"OwnerLink":{"@class":"BindingLink","targetId":{"uuid":"4368F9C6-FE91-443E-9C48-2F0B1099559F"}},"animation":{"uuid":"8E1CD1B0-F2A2-445E-BA6E-237DEF48D972"},"AnimationType":"object3D","is_imported":true,"isEnabled":true},{"@class":"AnimationScript","id":{"uuid":"A582F657-19BF-44C1-9981-C4E69F883E84"},"name":"AnimationScript","enableOnAwake":false,"OwnerLink":{"@class":"BindingLink","targetId":{"uuid":"BD90CAE1-DD13-4F2E-BA5F-65DDE14C87A8"}},"animation":{"uuid":"AE162935-494B-4ACF-B554-687570E0FDF7"},"AnimationType":"object3D","is_imported":true,"isEnabled":true},{"@class":"AnimationScript","id":{"uuid":"2C77F4ED-3B66-46AA-A064-714882F4B2ED"},"name":"AnimationScript","enableOnAwake":false,"OwnerLink":{"@class":"BindingLink","targetId":{"uuid":"B7769D39-C498-462E-BA23-3A416FA78BA5"}},"animation":{"uuid":"07342126-8BE0-4664-9694-93E1527BEC77"},"AnimationType":"object3D","is_imported":true,"isEnabled":true},{"@class":"AnimationScript","id":{"uuid":"FF6AFEE4-30A5-4F65-9DBD-C02EFCF33ACB"},"name":"AnimationScript","enableOnAwake":false,"OwnerLink":{"@class":"BindingLink","targetId":{"uuid":"E952260A-727A-4E91-9758-72743DC2A937"}},"animation":{"uuid":"9CA1B114-798D-4319-B4E7-0916879D9A8A"},"AnimationType":"object3D","is_imported":true,"isEnabled":true},{"@class":"AnimationScript","id":{"uuid":"3DD5DDD0-8717-4A1B-8E22-B0EE98B54B29"},"name":"AnimationScript","enableOnAwake":false,"OwnerLink":{"@class":"BindingLink","targetId":{"uuid":"6C9EF6F0-447A-44D4-89C5-B68F78FB06AB"}},"animation":{"uuid":"EAA1A75A-BF9A-48CC-8845-264BAA6BFBE4"},"AnimationType":"object3D","is_imported":true,"isEnabled":true},{"@class":"AnimationScript","id":{"uuid":"63FBAFA1-3B21-4F43-B31A-829727DE0AFA"},"name":"AnimationScript","enableOnAwake":false,"OwnerLink":{"@class":"BindingLink","targetId":{"uuid":"610894FA-0117-4342-819F-0DE4DE0FDB84"}},"animation":{"uuid":"C0CC87FE-072D-4F28-A0DC-29E5EA104C51"},"AnimationType":"object3D","is_imported":true,"isEnabled":true},{"@class":"AnimationScript","id":{"uuid":"5F90F82F-4247-4C13-83E9-22014558425E"},"name":"AnimationScript","enableOnAwake":false,"OwnerLink":{"@class":"BindingLink","targetId":{"uuid":"60ADB170-D610-43A8-9163-EFD492FA8FA2"}},"animation":{"uuid":"9AD8DF38-0CAA-4C9F-BC77-FFF382F7E4BC"},"AnimationType":"object3D","is_imported":true,"isEnabled":true}]},"triggers":[]}