{"@class":"TimeLineScript","id":{"uuid":"3208577D-4D23-4E4E-8E3F-6B912731FA6D"},"name":"Animation","enableOnAwake":false,"loop":false,"jumpToFirstFrameAtEnd":false,"speed":1.0,"weight":1.0,"loopStartTime":0,"loopDuration":0,"is_imported":false,"type":"user","scripts":{"@class":"StdListRuntimeScript","list":[{"@class":"AnimationScript","id":{"uuid":"9F3ED667-9432-47A6-B711-FA22DE92D619"},"name":"Selected State","enableOnAwake":false,"OwnerLink":{"@class":"BindingLink","targetId":{"uuid":"4CCE932F-3339-4795-A5CC-C5405D117E3D"}},"animation":{"uuid":"E0C399F2-8763-4CF2-A9C8-10B52C7092DE"},"AnimationType":"object3D","is_imported":false,"isEnabled":true}]},"triggers":[{"@class":"CollisionTrigger","id":{"uuid":"F493B768-3035-40F0-861B-32A089D96B8B"},"ownerScriptId":{"uuid":"3208577D-4D23-4E4E-8E3F-6B912731FA6D"},"logicOperation":0,"resultType":0,"isInverted":false,"eventType":"inside","targetBindingLink":{"@class":"BindingLink","targetId":{"uuid":"4CCE932F-3339-4795-A5CC-C5405D117E3D"}},"zoneBindingLink":{"@class":"BindingLink","targetId":{"uuid":"C6862789-CBDA-4AEB-A531-7B52D3DEB87C"}}},{"@class":"AnimationTrigger","id":{"uuid":"1B07E0B0-D898-4089-BF36-E6D708D6FCA5"},"ownerScriptId":{"uuid":"3208577D-4D23-4E4E-8E3F-6B912731FA6D"},"logicOperation":1,"resultType":0,"isInverted":false,"event":2,"bindingLink":{"@class":"BindingLink","targetId":{"uuid":"590D632C-C65C-4AA3-AABC-22231928BA43"}}}]}