{"@class":"TimeLineScript","id":{"uuid":"3C34DBB4-C819-4C2C-A92C-4FA568FE1BA6"},"name":"Animation","enableOnAwake":false,"loop":false,"jumpToFirstFrameAtEnd":false,"speed":1.0,"weight":1.0,"loopStartTime":0,"loopDuration":0,"is_imported":false,"type":"user","scripts":{"@class":"StdListRuntimeScript","list":[{"@class":"AnimationScript","id":{"uuid":"123FA6CE-964D-4B18-8CDE-A061E2808975"},"name":"gun_L","enableOnAwake":false,"OwnerLink":{"@class":"BindingLink","targetId":{"uuid":"E0CF5192-D69F-4FBB-9219-279EA5FC5DA0"},"targetRelativeAddress":{"@class":"NodeRelativeAddressBase","index":1,"name":"Drone_T-pose","subaddress":{"@class":"NodeRelativeAddressBase","index":1,"name":"Armature","subaddress":{"@class":"NodeRelativeAddressBase","index":0,"name":"BaseDR2","subaddress":{"@class":"NodeRelativeAddressBase","index":0,"name":"Body","subaddress":{"@class":"NodeRelativeAddressBase","index":0,"name":"turel_L","subaddress":{"@class":"NodeRelativeAddressBase","index":0,"name":"gun_L"}}}}}}},"animation":{"uuid":"848A4F48-4896-4DFA-B390-39BA175778DE"},"AnimationType":"object3D","is_imported":false,"isEnabled":true},{"@class":"AnimationScript","id":{"uuid":"666B1297-C5E1-40FF-9E73-1671C7A18489"},"name":"gun_R","enableOnAwake":false,"OwnerLink":{"@class":"BindingLink","targetId":{"uuid":"EE88980C-36BD-444F-A378-EE690FF6C635"},"targetRelativeAddress":{"@class":"NodeRelativeAddressBase","index":1,"name":"Drone_T-pose","subaddress":{"@class":"NodeRelativeAddressBase","index":1,"name":"Armature","subaddress":{"@class":"NodeRelativeAddressBase","index":0,"name":"BaseDR2","subaddress":{"@class":"NodeRelativeAddressBase","index":0,"name":"Body","subaddress":{"@class":"NodeRelativeAddressBase","index":2,"name":"turel_R","subaddress":{"@class":"NodeRelativeAddressBase","index":0,"name":"gun_R"}}}}}}},"animation":{"uuid":"37A5E0B0-06CB-42A4-BB11-E824F7F51261"},"AnimationType":"object3D","is_imported":false,"isEnabled":true}]},"triggers":[]}