{"@class":"TimeLineScript","id":{"uuid":"3D5B3057-435C-4EFC-95C5-4315DE1B5489"},"name":"Animation","enableOnAwake":false,"loop":false,"jumpToFirstFrameAtEnd":false,"speed":1.0,"weight":1.0,"loopStartTime":0,"loopDuration":0,"is_imported":false,"type":"user","scripts":{"@class":"StdListRuntimeScript","list":[{"@class":"AnimationScript","id":{"uuid":"AB75B802-FFE9-4CDA-96DF-0F33EA0EC1C1"},"name":"Drone 3","enableOnAwake":false,"OwnerLink":{"@class":"BindingLink","targetId":{"uuid":"51C3A4EB-3448-4559-B927-83E5AD1DE4EE"}},"animation":{"uuid":"F0FE1E9A-A9E1-4FEF-8453-817D6076FEF6"},"AnimationType":"object3D","is_imported":false,"isEnabled":true}]},"triggers":[{"@class":"CollisionTrigger","id":{"uuid":"1217D712-4DC1-4686-925F-843C88E297DA"},"ownerScriptId":{"uuid":"3D5B3057-435C-4EFC-95C5-4315DE1B5489"},"logicOperation":0,"resultType":0,"isInverted":false,"eventType":"in","targetBindingLink":{"@class":"BindingLink","targetId":{"uuid":"E749076B-6F2A-4FA4-B4D6-669A298591BB"}},"zoneBindingLink":{"@class":"BindingLink","targetId":{"uuid":"1F8B6620-4576-411E-A66E-2C1D7FB02240"}}},{"@class":"CollisionTrigger","id":{"uuid":"67F5EB9A-28A1-4387-B145-B142489F247A"},"ownerScriptId":{"uuid":"3D5B3057-435C-4EFC-95C5-4315DE1B5489"},"logicOperation":1,"resultType":0,"isInverted":true,"eventType":"out","targetBindingLink":{"@class":"BindingLink","targetId":{"uuid":"E749076B-6F2A-4FA4-B4D6-669A298591BB"}},"zoneBindingLink":{"@class":"BindingLink","targetId":{"uuid":"1F8B6620-4576-411E-A66E-2C1D7FB02240"}}}]}