{"@class":"TimeLineScript","id":{"uuid":"46472F45-D5C0-43D0-A9A4-F474639B7888"},"name":"Animation","enableOnAwake":false,"loop":false,"jumpToFirstFrameAtEnd":false,"speed":1.0,"weight":1.0,"loopStartTime":0,"loopDuration":0,"is_imported":false,"type":"user","scripts":{"@class":"StdListRuntimeScript","list":[{"@class":"AnimationScript","id":{"uuid":"360834B8-9EF3-44CB-8409-42F6E70DC6AE"},"name":"Tempx","enableOnAwake":false,"OwnerLink":{"@class":"BindingLink","targetId":{"uuid":"F220BD9E-B604-441D-A4C4-A1D01924028C"}},"animation":{"uuid":"8B0FF76D-7709-42DF-9CBD-A3DE5279AFBB"},"AnimationType":"avar","is_imported":false,"isEnabled":true},{"@class":"AnimationScript","id":{"uuid":"5AE46514-5672-47A0-9305-D22590FEF2E9"},"name":"TempY","enableOnAwake":false,"OwnerLink":{"@class":"BindingLink","targetId":{"uuid":"C5D3DBF7-C9D6-4C16-8A1E-51A8710500D4"}},"animation":{"uuid":"EFD75A9D-2103-42C0-8061-2B2C27AD9481"},"AnimationType":"avar","is_imported":false,"isEnabled":true},{"@class":"AnimationScript","id":{"uuid":"EC649E71-70D7-4E62-8AD6-75CC508176CB"},"name":"TempZ","enableOnAwake":false,"OwnerLink":{"@class":"BindingLink","targetId":{"uuid":"26FC1101-1EE0-4773-AF79-21BF4226BA1D"}},"animation":{"uuid":"063FDD31-B7E5-401C-A398-2140ACA042EC"},"AnimationType":"avar","is_imported":false,"isEnabled":true},{"@class":"AnimationScript","id":{"uuid":"AFD5E5FF-5AA4-47EC-9945-7496510139F5"},"name":"Bullet_Hole","enableOnAwake":false,"OwnerLink":{"@class":"BindingLink","targetId":{"uuid":"5A80D319-5963-450D-B310-2C057559C1CF"}},"animation":{"uuid":"31E11D2A-1AB0-4781-BFB2-6402FAF72E93"},"AnimationType":"object3D","is_imported":false,"isEnabled":true},{"@class":"AnimationScript","id":{"uuid":"191F5353-8D25-41B0-8032-524DC96D9C3A"},"name":"Bullet_Impact 1","enableOnAwake":false,"OwnerLink":{"@class":"BindingLink","targetId":{"uuid":"ED6EB1AD-DE94-4A5A-BDA5-9CCC55CAFFD3"}},"animation":{"uuid":"CCA8A69A-66B8-41DB-BC0A-348DE1D94272"},"AnimationType":"object3D","is_imported":false,"isEnabled":true},{"@class":"AnimationScript","id":{"uuid":"51BDD7B9-A275-44BF-A99D-C6AB24A87A08"},"name":"Fake_Bullet","enableOnAwake":false,"OwnerLink":{"@class":"BindingLink","targetId":{"uuid":"501F758B-BD1F-4404-9C47-E34B5E9F2351"}},"animation":{"uuid":"9B61D42E-8FBC-40A4-AF9D-53C813FD6B92"},"AnimationType":"object3D","is_imported":false,"isEnabled":true},{"@class":"AnimationScript","id":{"uuid":"7F5E32AA-5552-472B-8232-DECB6ACEDBE6"},"name":"Glass_part 1","enableOnAwake":false,"OwnerLink":{"@class":"BindingLink","targetId":{"uuid":"A9BEE097-B9C4-463F-B607-885AAA819554"},"targetRelativeAddress":{"@class":"NodeRelativeAddressBase","index":5,"name":"Glass_Hole 1","subaddress":{"@class":"NodeRelativeAddressBase","index":2,"name":"Glass_part 1"}}},"animation":{"uuid":"BA740539-F09C-415D-B7E3-4AC5DF26F383"},"AnimationType":"object3D","is_imported":false,"isEnabled":true}]},"triggers":[{"@class":"GroupTrigger","id":{"uuid":"53DF89EF-BE70-48F3-A110-10BD83FEEFC9"},"ownerScriptId":{"uuid":"46472F45-D5C0-43D0-A9A4-F474639B7888"},"logicOperation":1,"resultType":2366,"isInverted":false,"triggers":[{"@class":"CollisionTrigger","id":{"uuid":"AF8FD880-37B4-4F16-BD9B-C9117D732BCB"},"ownerScriptId":{"uuid":"46472F45-D5C0-43D0-A9A4-F474639B7888"},"logicOperation":1,"resultType":0,"isInverted":false,"eventType":"in","targetBindingLink":{"@class":"BindingLink","targetId":{"uuid":"501F758B-BD1F-4404-9C47-E34B5E9F2351"}},"zoneBindingLink":{"@class":"BindingLink","tagId":{"uuid":"F2A13C2E-E20E-46A8-BAF6-9B2FE839588D"}}},{"@class":"CompareTrigger","id":{"uuid":"77B72AA2-CFC0-425D-83B6-6A8DABB4152C"},"ownerScriptId":{"uuid":"46472F45-D5C0-43D0-A9A4-F474639B7888"},"logicOperation":1,"resultType":0,"isInverted":false,"operation":"==","eventType":"result_true","leftOperand":"object__ED6EB1AD_DE94_4A5A_BDA5_9CCC55CAFFD3__HoleNum","rightOperand":"4"}]},{"@class":"AnimationTrigger","id":{"uuid":"2D8990EF-4D08-446E-9E00-523860C88786"},"ownerScriptId":{"uuid":"46472F45-D5C0-43D0-A9A4-F474639B7888"},"logicOperation":0,"resultType":3,"isInverted":false,"event":1,"bindingLink":{"@class":"BindingLink","targetId":{"uuid":"8E411CCC-E903-47C9-9F19-D4ED0B19FE53"}}}],"symbolTable":{"@class":"VariousSymbolTable","id":{"uuid":"746CA618-D300-4505-9756-3D195B8E2FF5"},"variables":[{"@class":"VariantVariable","id":{"uuid":"F220BD9E-B604-441D-A4C4-A1D01924028C"},"name":"Tempx","type":"float","value":-517.0925903320313},{"@class":"VariantVariable","id":{"uuid":"26FC1101-1EE0-4773-AF79-21BF4226BA1D"},"name":"TempZ","type":"float","value":120.04640197753906},{"@class":"VariantVariable","id":{"uuid":"C5D3DBF7-C9D6-4C16-8A1E-51A8710500D4"},"name":"TempY","type":"float","value":58.70154571533203}]}}