{"@class":"TimeLineScript","id":{"uuid":"54410AE5-DA09-40A1-8552-FA3118D7AD1B"},"name":"Animation","enableOnAwake":false,"loop":false,"jumpToFirstFrameAtEnd":false,"speed":1.0,"weight":1.0,"loopStartTime":0,"loopDuration":0,"is_imported":false,"type":"user","scripts":{"@class":"StdListRuntimeScript","list":[{"@class":"AnimationScript","id":{"uuid":"DFC511BC-6CC5-4B47-A7C5-8ADD633F1719"},"name":"Traget Ray","enableOnAwake":false,"OwnerLink":{"@class":"BindingLink","targetId":{"uuid":"AC91C5D0-D155-4381-8F40-CB1E189DB038"},"targetRelativeAddress":{"@class":"NodeRelativeAddressBase","index":0,"name":"Drone 2","subaddress":{"@class":"NodeRelativeAddressBase","index":3,"name":"Target Ray Y","subaddress":{"@class":"NodeRelativeAddressBase","index":0,"name":"Target Ray X","subaddress":{"@class":"NodeRelativeAddressBase","index":0,"name":"Target Ray"}}}}},"animation":{"uuid":"20B79360-4860-4946-AB3D-76263DD90BF1"},"AnimationType":"object3D","is_imported":false,"isEnabled":true},{"@class":"AnimationScript","id":{"uuid":"582A69A3-4443-45BA-BC88-340EEE331430"},"name":"Shoot Ray","enableOnAwake":false,"OwnerLink":{"@class":"BindingLink","targetId":{"uuid":"F6F2F27B-152F-4865-B5FE-825C144A3E2E"},"targetRelativeAddress":{"@class":"NodeRelativeAddressBase","index":0,"name":"Drone 2","subaddress":{"@class":"NodeRelativeAddressBase","index":1,"name":"Drone_T-pose","subaddress":{"@class":"NodeRelativeAddressBase","index":1,"name":"Armature","subaddress":{"@class":"NodeRelativeAddressBase","index":0,"name":"BaseDR2","subaddress":{"@class":"NodeRelativeAddressBase","index":0,"name":"Body","subaddress":{"@class":"NodeRelativeAddressBase","index":2,"name":"turel_R","subaddress":{"@class":"NodeRelativeAddressBase","index":3,"name":"Shoot Ray"}}}}}}}},"animation":{"uuid":"0B37E6D8-F177-4960-AB47-ED731EC5667D"},"AnimationType":"object3D","is_imported":false,"isEnabled":true}]},"triggers":[{"@class":"CollisionTrigger","id":{"uuid":"67A7742E-8FB5-4170-9FE6-48BEAA0E4EF0"},"ownerScriptId":{"uuid":"54410AE5-DA09-40A1-8552-FA3118D7AD1B"},"logicOperation":0,"resultType":0,"isInverted":false,"eventType":"out","targetBindingLink":{"@class":"BindingLink","targetId":{"uuid":"E18FB7FF-7774-43D0-8C5E-16752EC1EB0F"}},"zoneBindingLink":{"@class":"BindingLink","targetId":{"uuid":"25FE1577-F604-4D13-ACCD-656144CA9EBD"}}}]}