{"@class":"TimeLineScript","id":{"uuid":"849A064E-04D0-4366-A121-EA53B1ADFC62"},"name":"Animation","enableOnAwake":false,"loop":false,"jumpToFirstFrameAtEnd":false,"speed":1.0,"weight":1.0,"loopStartTime":0,"loopDuration":0,"is_imported":false,"type":"user","scripts":{"@class":"StdListRuntimeScript","list":[{"@class":"AnimationScript","id":{"uuid":"CD9E9BE9-B57D-44D4-ADC1-F7EB5DA2F3BA"},"name":"Fluid pool 3","enableOnAwake":false,"OwnerLink":{"@class":"BindingLink","targetId":{"uuid":"5EE0D01F-6710-4109-BCBE-28FC3CB2F4E5"},"targetRelativeAddress":{"@class":"NodeRelativeAddressBase","index":3,"name":"Fluid pool 3"}},"animation":{"uuid":"C41E4224-A85A-4EC0-9091-F2BAD7CB2414"},"AnimationType":"object3D","is_imported":false,"isEnabled":true},{"@class":"AnimationScript","id":{"uuid":"0DE7B82D-174F-488C-8E9D-EC65060328F0"},"name":"RU","enableOnAwake":false,"OwnerLink":{"@class":"BindingLink","targetId":{"uuid":"1EC709DA-7BF7-44EB-A027-9D9A6C4B6A2E"}},"animation":{"uuid":"BEDBF456-C97E-488B-83DB-D95C2FD8780A"},"AnimationType":"avar","is_imported":false,"isEnabled":true},{"@class":"AnimationScript","id":{"uuid":"2530C1B7-1E5F-4FC9-89A7-738B0E963C3D"},"name":"RV","enableOnAwake":false,"OwnerLink":{"@class":"BindingLink","targetId":{"uuid":"C5E9A37E-C93C-4577-A8D0-DB28459EB6A7"}},"animation":{"uuid":"E026EAC7-BCBA-4650-A2E3-3999D2CBDB8D"},"AnimationType":"avar","is_imported":false,"isEnabled":true},{"@class":"AnimationScript","id":{"uuid":"899D5692-1786-476E-93ED-778C00D38F8A"},"name":"Speaker","enableOnAwake":false,"OwnerLink":{"@class":"BindingLink","targetId":{"uuid":"1F026308-8E3D-4DBE-93B1-9486C92EC127"},"targetRelativeAddress":{"@class":"NodeRelativeAddressBase","index":8,"name":"Toxic Pool 5a","subaddress":{"@class":"NodeRelativeAddressBase","index":1,"name":"Speaker"}}},"animation":{"uuid":"379DE421-DA07-44C8-8355-A77392E25A0B"},"AnimationType":"object3D","is_imported":false,"isEnabled":true},{"@class":"AnimationScript","id":{"uuid":"B1DA4314-F94D-41F5-93BB-845FFC7AC6C8"},"name":"Toxic Spit 5","enableOnAwake":false,"OwnerLink":{"@class":"BindingLink","targetId":{"uuid":"D5E5AA94-DBEA-4327-9AF0-5C668D801C34"}},"animation":{"uuid":"02826052-E94B-4D93-BF85-F357CFA3B07E"},"AnimationType":"object3D","is_imported":false,"isEnabled":true}]},"triggers":[{"@class":"CompareTrigger","id":{"uuid":"D8500648-956C-4B39-8927-08C438B50CAA"},"ownerScriptId":{"uuid":"849A064E-04D0-4366-A121-EA53B1ADFC62"},"logicOperation":0,"resultType":0,"isInverted":false,"operation":"==","eventType":"result_true_started","leftOperand":"object__D5E5AA94_DBEA_4327_9AF0_5C668D801C34__pool_num","rightOperand":"true"},{"@class":"AnimationTrigger","id":{"uuid":"D1E5C905-FEF8-42CB-ABB1-B483D13C4D9F"},"ownerScriptId":{"uuid":"849A064E-04D0-4366-A121-EA53B1ADFC62"},"logicOperation":0,"resultType":0,"isInverted":false,"event":1,"bindingLink":{"@class":"BindingLink","targetId":{"uuid":"D8C45368-3452-4D06-B4DC-0E262D08EA03"}}}],"symbolTable":{"@class":"VariousSymbolTable","id":{"uuid":"2ED588AE-04B9-4351-9493-722CB974E078"},"variables":[{"@class":"VariantVariable","id":{"uuid":"1EC709DA-7BF7-44EB-A027-9D9A6C4B6A2E"},"name":"RU","type":"float","value":0.0},{"@class":"VariantVariable","id":{"uuid":"C5E9A37E-C93C-4577-A8D0-DB28459EB6A7"},"name":"RV","type":"float","value":0.0}]}}