{"@class":"TimeLineScript","id":{"uuid":"EAF1D450-02D1-4137-8F41-ADB7C683F170"},"name":"Animation","enableOnAwake":false,"loop":false,"jumpToFirstFrameAtEnd":false,"speed":1.0,"weight":1.0,"loopStartTime":0,"loopDuration":0,"is_imported":false,"type":"user","scripts":{"@class":"StdListRuntimeScript","list":[{"@class":"AnimationScript","id":{"uuid":"1AA65244-D9D4-4300-A4DA-7910022D3210"},"name":"Tempx","enableOnAwake":false,"OwnerLink":{"@class":"BindingLink","targetId":{"uuid":"F220BD9E-B604-441D-A4C4-A1D01924028C"}},"animation":{"uuid":"87EC2523-4FE1-4567-85D7-1A0D6C9BE135"},"AnimationType":"avar","is_imported":false,"isEnabled":true},{"@class":"AnimationScript","id":{"uuid":"9823AF70-E12E-4C72-8683-78CFBC91F5C0"},"name":"TempY","enableOnAwake":false,"OwnerLink":{"@class":"BindingLink","targetId":{"uuid":"C5D3DBF7-C9D6-4C16-8A1E-51A8710500D4"}},"animation":{"uuid":"AC606174-EFBD-4C86-97FF-B02D600C243D"},"AnimationType":"avar","is_imported":false,"isEnabled":true},{"@class":"AnimationScript","id":{"uuid":"1B3A5C04-B5CA-4DD9-A6F7-3446B7B818B1"},"name":"TempZ","enableOnAwake":false,"OwnerLink":{"@class":"BindingLink","targetId":{"uuid":"26FC1101-1EE0-4773-AF79-21BF4226BA1D"}},"animation":{"uuid":"75DABE9D-951C-462D-998C-F0C1305ECF58"},"AnimationType":"avar","is_imported":false,"isEnabled":true},{"@class":"AnimationScript","id":{"uuid":"3D1A13FB-EE21-4A32-BDDC-1E2E5839FB48"},"name":"Bullet_Hole","enableOnAwake":false,"OwnerLink":{"@class":"BindingLink","targetId":{"uuid":"41ABBB75-FD22-4734-8FAD-6A930ADAF7CF"},"targetRelativeAddress":{"@class":"NodeRelativeAddressBase","index":3,"name":"Bullet_Hole"}},"animation":{"uuid":"A79AC979-F944-4E04-A964-A353156F8BF5"},"AnimationType":"object3D","is_imported":false,"isEnabled":true},{"@class":"AnimationScript","id":{"uuid":"BA17F254-3188-446F-B41B-9714E355BF33"},"name":"Fake_Bullet","enableOnAwake":false,"OwnerLink":{"@class":"BindingLink","targetId":{"uuid":"501F758B-BD1F-4404-9C47-E34B5E9F2351"}},"animation":{"uuid":"C7B974A1-06B9-40FE-8DFE-6D2907A6596E"},"AnimationType":"object3D","is_imported":false,"isEnabled":true},{"@class":"AnimationScript","id":{"uuid":"4C5E82C9-804E-4E77-B95B-E0367188BD5D"},"name":"Observ_Window_Back","enableOnAwake":false,"OwnerLink":{"@class":"BindingLink","targetId":{"uuid":"784137AB-23C0-408B-943A-0CDAA13072C5"}},"animation":{"uuid":"590DC831-5718-41C2-9281-18D6CD898314"},"AnimationType":"object3D","is_imported":false,"isEnabled":true},{"@class":"AnimationScript","id":{"uuid":"C3B7B9C3-2149-49AF-B13D-09941E59473D"},"name":"Glass_part 1","enableOnAwake":false,"OwnerLink":{"@class":"BindingLink","targetId":{"uuid":"C264B368-6622-4832-AE5F-C815FA43FC38"},"targetRelativeAddress":{"@class":"NodeRelativeAddressBase","index":5,"name":"Glass_Hole 1","subaddress":{"@class":"NodeRelativeAddressBase","index":2,"name":"Glass_part 1"}}},"animation":{"uuid":"E9570A57-01DF-4C20-951B-4098EB9A9E64"},"AnimationType":"object3D","is_imported":false,"isEnabled":true}]},"triggers":[{"@class":"CollisionTrigger","id":{"uuid":"37DC8E2A-75D3-47C7-99B3-6A0BD87210CD"},"ownerScriptId":{"uuid":"EAF1D450-02D1-4137-8F41-ADB7C683F170"},"logicOperation":1,"resultType":0,"isInverted":false,"eventType":"in","targetBindingLink":{"@class":"BindingLink","targetId":{"uuid":"501F758B-BD1F-4404-9C47-E34B5E9F2351"}},"zoneBindingLink":{"@class":"BindingLink","targetId":{"uuid":"784137AB-23C0-408B-943A-0CDAA13072C5"}}},{"@class":"CompareTrigger","id":{"uuid":"FDDEB38D-C05D-467D-A8BD-D6A7F83E681B"},"ownerScriptId":{"uuid":"EAF1D450-02D1-4137-8F41-ADB7C683F170"},"logicOperation":1,"resultType":0,"isInverted":false,"operation":"==","eventType":"result_true","leftOperand":"object__784137AB_23C0_408B_943A_0CDAA13072C5__HoleNum","rightOperand":"3"},{"@class":"AnimationTrigger","id":{"uuid":"85322F9A-2907-46B5-B242-A5FA824BF662"},"ownerScriptId":{"uuid":"EAF1D450-02D1-4137-8F41-ADB7C683F170"},"logicOperation":0,"resultType":3,"isInverted":false,"event":3,"bindingLink":{"@class":"BindingLink","targetId":{"uuid":"6E2CA2F4-D803-4294-87EB-747CC2981FEC"}}}],"symbolTable":{"@class":"VariousSymbolTable","id":{"uuid":"746CA618-D300-4505-9756-3D195B8E2FF5"},"variables":[{"@class":"VariantVariable","id":{"uuid":"F220BD9E-B604-441D-A4C4-A1D01924028C"},"name":"Tempx","type":"float","value":-40.673789978027347},{"@class":"VariantVariable","id":{"uuid":"26FC1101-1EE0-4773-AF79-21BF4226BA1D"},"name":"TempZ","type":"float","value":178.47222900390626},{"@class":"VariantVariable","id":{"uuid":"C5D3DBF7-C9D6-4C16-8A1E-51A8710500D4"},"name":"TempY","type":"float","value":0.829795241355896}]}}