{"@class":"Animation","id":{"uuid":"012E943C-B9FA-4E99-8FD8-8D68DA95A71F"},"tracks":[{"@class":"BoolBehaviorTrack","clips":[{"@class":"BoolBehaviorClip","beginTime":0,"duration":400,"script":"BoolValueBehaviorClipScript","behavior":{"@class":"BoolDiscreteBehavior","frames":[{"@class":"BoolKeyFrame","formula":{"@class":"BoolExpressionFormula","expression":"true"},"time":100},{"@class":"BoolKeyFrame","formula":{"@class":"BoolExpressionFormula","expression":"false"},"time":400}]}}],"script":"BoolBehaviorTrackScript","accessor":"ComponentPhysBodyEnabledAccessor"}]}