{"@class":"Animation","id":{"uuid":"166A0555-2EFF-4FEC-B165-F7E423A73EFC"},"tracks":[{"@class":"FloatBehaviorTrack","clips":[{"@class":"FloatBehaviorClip","beginTime":0,"duration":5000,"script":"FloatValueBehaviorClipScript","behavior":{"@class":"FloatBezierBehavior","frames":[{"@class":"FloatBezierKeyFrame","formula":{"@class":"FloatExpressionFormula","expression":"100"},"time":0,"point1":{"values":[0.0,0.0]},"point2":{"values":[0.0,0.0]},"order":"linear","transition":true},{"@class":"FloatBezierKeyFrame","formula":{"@class":"FloatExpressionFormula","expression":"0"},"time":5000,"point1":{"values":[0.0,0.0]},"point2":{"values":[0.0,0.0]},"order":"linear","transition":true}]}}],"script":"FloatBehaviorTrackScript","accessor":"OpacityBlendAccessor"},{"@class":"FloatBehaviorTrack","clips":[{"@class":"FloatBehaviorClip","beginTime":0,"duration":5000,"script":"FloatValueBehaviorClipScript","behavior":{"@class":"FloatBezierBehavior","frames":[{"@class":"FloatBezierKeyFrame","formula":{"@class":"FloatExpressionFormula","expression":"origin"},"time":0,"point1":{"values":[0.0,0.0]},"point2":{"values":[0.0,0.0]},"order":"linear","transition":true},{"@class":"FloatBezierKeyFrame","formula":{"@class":"FloatExpressionFormula","expression":"origin+0.25"},"time":5000,"point1":{"values":[0.0,0.0]},"point2":{"values":[0.0,0.0]},"order":"linear","transition":true}]}}],"script":"FloatBehaviorTrackScript","accessor":"OffsetUBlendAccessor"}]}