{"@class":"Animation","id":{"uuid":"3FC2060A-F5CC-4FC7-B270-8D0A0B5AD115"},"tracks":[{"@class":"Vector3BehaviorTrack","clips":[{"@class":"Vector3BehaviorClip","beginTime":0,"duration":799,"script":"Vector3ValueBehaviorClipScript","behavior":{"@class":"Vector3PlainBehavior","times":[0,799],"values":[0.009647972881793976,0.08587116003036499,-0.006284097209572792,0.009647957980632782,0.08587111532688141,-0.006284162402153015]}}],"script":"Vector3BehaviorTrackScript","accessor":"PositionBlendAccessor"},{"@class":"QuaternionBehaviorTrack","clips":[{"@class":"QuaternionBehaviorClip","beginTime":0,"duration":799,"script":"QuaternionValueBehaviorClipScript","behavior":{"@class":"QuaternionPlainBehavior","times":[0,799],"values":[-0.08475149422883988,0.991773247718811,-0.08918887376785279,-0.03533215820789337,-0.08475147932767868,0.991773247718811,-0.08918885886669159,-0.03533216193318367]}}],"script":"QuaternionBehaviorTrackScript","accessor":"RotationQBlendAccessor"},{"@class":"Vector3BehaviorTrack","clips":[{"@class":"Vector3BehaviorClip","beginTime":0,"duration":799,"script":"Vector3ValueBehaviorClipScript","behavior":{"@class":"Vector3PlainBehavior","times":[0,799],"values":[1.0,0.9999998807907105,1.0,1.0,0.9999999403953552,1.0000001192092896]}}],"script":"Vector3BehaviorTrackScript","accessor":"ScaleBlendAccessor"}]}