{"@class":"Animation","id":{"uuid":"6308B7D1-28C6-41CA-A2DB-15332520C1D6"},"tracks":[{"@class":"SoundTrack","clips":[{"@class":"SoundClip","beginTime":0,"duration":167,"script":"SoundClipScript","behavior":{"@class":"SoundSampleBehavior","volume":1.0,"volumeModulation":0.0,"pitch":0.9511312246322632,"pitchModulation":0.0,"soundSampleId":{"uuid":"19CDD217-00C0-4FF6-88D1-F5DD80588CF2"}},"color":{"values":[0.8509804010391235,0.5882353186607361,0.2549019753932953]}}],"script":"SoundTrackScript","accessor":"AudioSourceAccessor","volume":1.0}]}