{"@class":"Animation","id":{"uuid":"6865E628-B217-4524-BD53-26179CC83579"},"tracks":[{"@class":"TimeLineTrack","clips":[{"@class":"TimeLineClip","beginTime":1000,"duration":1333,"script":"TimeLineClipScript","behavior":{"@class":"TimeLineBehavior","speed":1.0,"weights":{}},"bindinglink":{"@class":"BindingLink","targetId":{"uuid":"0FCA9271-F4DA-4880-8FE9-A4936DF6F62E"}},"color":{"values":[0.0,0.0,0.0]}},{"@class":"TimeLineClip","beginTime":2400,"duration":1333,"script":"TimeLineClipScript","behavior":{"@class":"TimeLineBehavior","speed":1.0,"weights":{}},"bindinglink":{"@class":"BindingLink","targetId":{"uuid":"0FCA9271-F4DA-4880-8FE9-A4936DF6F62E"}},"color":{"values":[0.0,0.0,0.0]}},{"@class":"TimeLineClip","beginTime":3800,"duration":7500,"script":"TimeLineClipScript","behavior":{"@class":"TimeLineBehavior","speed":1.0,"weights":{}},"bindinglink":{"@class":"BindingLink","targetId":{"uuid":"AFD43D87-0959-4692-B585-60BCF558D086"}},"color":{"values":[0.0,0.0,0.0]}},{"@class":"TimeLineClip","beginTime":13000,"duration":2089,"script":"TimeLineClipScript","behavior":{"@class":"TimeLineBehavior","speed":1.0,"weights":{}},"bindinglink":{"@class":"BindingLink","targetId":{"uuid":"464140C0-5F8E-42F1-8D5C-81EC23CA7DF5"}},"color":{"values":[0.0,0.0,0.0]}},{"@class":"TimeLineClip","beginTime":17000,"duration":2089,"script":"TimeLineClipScript","behavior":{"@class":"TimeLineBehavior","speed":1.0,"weights":{}},"bindinglink":{"@class":"BindingLink","targetId":{"uuid":"E453DD62-3E9A-42EB-9D74-6B2C8269297D"}},"color":{"values":[0.0,0.0,0.0]}},{"@class":"TimeLineClip","beginTime":0,"duration":0,"script":"TimeLineClipScript","behavior":{"@class":"TimeLineBehavior","speed":1.0,"weights":{}},"bindinglink":{"@class":"BindingLink","targetId":{"uuid":"BFF0FB76-287C-43A5-B33E-AE7270768ABE"}},"color":{"values":[0.0,0.0,0.0]}},{"@class":"TimeLineClip","beginTime":19190,"duration":10,"script":"TimeLineClipScript","behavior":{"@class":"TimeLineBehavior","speed":1.0,"weights":{}},"bindinglink":{"@class":"BindingLink","targetId":{"uuid":"AC883671-D6DA-434E-91F5-68E331BA3986"}},"color":{"values":[0.0,0.0,0.0]}}],"script":"TimeLineTrackScript","accessor":"TimeLineAccessor"}]}