{"@class":"Animation","id":{"uuid":"69A513C2-D97A-4208-8AD0-85EE054EF2C6"},"tracks":[{"@class":"FloatBehaviorTrack","clips":[{"@class":"FloatBehaviorClip","beginTime":0,"duration":100,"script":"FloatValueBehaviorClipScript","behavior":{"@class":"FloatBezierBehavior","frames":[{"@class":"FloatBezierKeyFrame","formula":{"@class":"FloatExpressionFormula","expression":"1"},"time":100,"point1":{"values":[0.0,0.0]},"point2":{"values":[0.0,0.0]},"order":"linear","transition":true}]}}],"script":"FloatBehaviorTrackScript","accessor":"FloatVariableAccessor","attribute":"Index"},{"@class":"FloatBehaviorTrack","clips":[{"@class":"FloatBehaviorClip","beginTime":0,"duration":100,"script":"FloatValueBehaviorClipScript","behavior":{"@class":"FloatBezierBehavior","frames":[{"@class":"FloatBezierKeyFrame","formula":{"@class":"FloatExpressionFormula","expression":"getGlobalPositionX('B1P 1')"},"time":100,"point1":{"values":[0.0,0.0]},"point2":{"values":[0.0,0.0]},"order":"linear","transition":true}]}}],"script":"FloatBehaviorTrackScript","disabled":true,"accessor":"PositionXBlendAccessor"},{"@class":"FloatBehaviorTrack","clips":[{"@class":"FloatBehaviorClip","beginTime":0,"duration":100,"script":"FloatValueBehaviorClipScript","behavior":{"@class":"FloatBezierBehavior","frames":[{"@class":"FloatBezierKeyFrame","formula":{"@class":"FloatExpressionFormula","expression":"getGlobalPositionY('B1P 1')"},"time":100,"point1":{"values":[0.0,0.0]},"point2":{"values":[0.0,0.0]},"order":"linear","transition":true}]}}],"script":"FloatBehaviorTrackScript","disabled":true,"accessor":"PositionYBlendAccessor"},{"@class":"FloatBehaviorTrack","clips":[{"@class":"FloatBehaviorClip","beginTime":0,"duration":100,"script":"FloatValueBehaviorClipScript","behavior":{"@class":"FloatBezierBehavior","frames":[{"@class":"FloatBezierKeyFrame","formula":{"@class":"FloatExpressionFormula","expression":"getGlobalPositionZ('B1P 1')"},"time":100,"point1":{"values":[0.0,0.0]},"point2":{"values":[0.0,0.0]},"order":"linear","transition":true}]}}],"script":"FloatBehaviorTrackScript","disabled":true,"accessor":"PositionZBlendAccessor"}]}