{"@class":"Animation","id":{"uuid":"8B736711-F57F-4F4A-866C-FBAFEAABEB21"},"tracks":[{"@class":"Vector3BehaviorTrack","clips":[{"@class":"Vector3BehaviorClip","beginTime":0,"duration":33,"script":"Vector3ValueBehaviorClipScript","behavior":{"@class":"Vector3PlainBehavior","times":[0,33],"values":[0.02948376163840294,0.1045648381114006,-5.813598704662581e-7,0.02948376163840294,0.10456464439630509,-6.055831818230217e-7]}}],"script":"Vector3BehaviorTrackScript","accessor":"PositionBlendAccessor"},{"@class":"QuaternionBehaviorTrack","clips":[{"@class":"QuaternionBehaviorClip","beginTime":0,"duration":33,"script":"QuaternionValueBehaviorClipScript","behavior":{"@class":"QuaternionPlainBehavior","times":[0,33],"values":[0.062486425042152408,0.007975805550813675,-0.061897438019514087,0.9960926175117493,0.0624864287674427,0.007975835353136063,-0.061897438019514087,0.9960926175117493]}}],"script":"QuaternionBehaviorTrackScript","accessor":"RotationQBlendAccessor"},{"@class":"Vector3BehaviorTrack","clips":[{"@class":"Vector3BehaviorClip","beginTime":0,"duration":33,"script":"Vector3ValueBehaviorClipScript","behavior":{"@class":"Vector3PlainBehavior","times":[0,33],"values":[1.0,1.0,0.9999999403953552,1.0,0.9999999403953552,1.0]}}],"script":"Vector3BehaviorTrackScript","accessor":"ScaleBlendAccessor"}]}