{"@class":"Animation","id":{"uuid":"B9712808-D27E-42C0-9780-9A805F6CA744"},"tracks":[{"@class":"FloatBehaviorTrack","clips":[{"@class":"FloatBehaviorClip","beginTime":0,"duration":0,"script":"FloatValueBehaviorClipScript","behavior":{"@class":"FloatBezierBehavior","frames":[{"@class":"FloatBezierKeyFrame","formula":{"@class":"FloatExpressionFormula","expression":"4"},"time":0,"point1":{"values":[0.0,0.0]},"point2":{"values":[0.0,0.0]},"order":"linear","transition":true}]}}],"script":"FloatBehaviorTrackScript","accessor":"TilingUBlendAccessor"},{"@class":"FloatBehaviorTrack","clips":[{"@class":"FloatBehaviorClip","beginTime":0,"duration":0,"script":"FloatValueBehaviorClipScript","behavior":{"@class":"FloatBezierBehavior","frames":[{"@class":"FloatBezierKeyFrame","formula":{"@class":"FloatExpressionFormula","expression":"2"},"time":0,"point1":{"values":[0.0,0.0]},"point2":{"values":[0.0,0.0]},"order":"linear","transition":true}]}}],"script":"FloatBehaviorTrackScript","accessor":"TilingVBlendAccessor"}]}