{"@class":"Animation","id":{"uuid":"FABA5CA8-8B64-451A-8D06-C1DD4E5EC34A"},"tracks":[{"@class":"BoolBehaviorTrack","clips":[{"@class":"BoolBehaviorClip","beginTime":0,"duration":0,"script":"BoolValueBehaviorClipScript","behavior":{"@class":"BoolDiscreteBehavior","frames":[{"@class":"BoolKeyFrame","formula":{"@class":"BoolExpressionFormula","expression":"false"},"time":0}]}}],"script":"BoolBehaviorTrackScript","accessor":"Object3DEnabledBlendAccessor"},{"@class":"BoolBehaviorTrack","clips":[{"@class":"BoolBehaviorClip","beginTime":0,"duration":0,"script":"BoolValueBehaviorClipScript","behavior":{"@class":"BoolDiscreteBehavior","frames":[{"@class":"BoolKeyFrame","formula":{"@class":"BoolExpressionFormula","expression":"false"},"time":0}]}}],"script":"BoolBehaviorTrackScript","accessor":"ComponentPhysBodyEnabledAccessor"}]}